saust/Constants.py
saust/TestCase.py
saust/__init__.py
saust/__main__.py
saust/GUI/ColorizeFunctions.py
saust/GUI/DataTable.py
saust/GUI/Editor.py
saust/GUI/Graphics.py
saust/GUI/MainWindow.py
saust/GUI/PageXML.py
saust/GUI/PopUpWindow.py
saust/GUI/Steps.py
saust/GUI/__init__.py
saust/GUI/GraphicsWidgets/StepsTable.py
saust/GUI/GraphicsWidgets/TestCaseTable.py
saust/GUI/GraphicsWidgets/__init__.py
saust/Tools/ExecuteMethods.py
saust/Tools/LoadXML.py
saust/Tools/ResultsPDF.py
saust/Tools/TestData.py
saust/Tools/__init__.py
saust-0.15.131.dist-info/LICENSE
saust-0.15.131.dist-info/METADATA
saust-0.15.131.dist-info/WHEEL
saust-0.15.131.dist-info/top_level.txt
saust-0.15.131.dist-info/RECORD
